classes_aux/__init__.py
classes_aux/annot_1_aux.py
classes_aux/annot_2_all_defined.py
classes_aux/annot_3_iter_values.py
classes_aux/annot_4_cls_keys_as_values.py
classes_aux/cmp.py
classes_aux/getattr_0_echo.py
classes_aux/getattr_1_aux.py
classes_aux/getattr_2_anycase.py
classes_aux/getattr_3_prefix_1_inst.py
classes_aux/getattr_3_prefix_2_cls.py
classes_aux/middle_group.py
classes_aux/number.py
classes_aux/static.py
classes_aux-0.2.0.dist-info/LICENSE
classes_aux-0.2.0.dist-info/METADATA
classes_aux-0.2.0.dist-info/WHEEL
classes_aux-0.2.0.dist-info/top_level.txt
classes_aux-0.2.0.dist-info/RECORD
