Metadata-Version: 2.1
Name: classes_aux
Version: 0.2.0
Summary: attempt to keep all useful classes and classesTemplates in one place
Home-page: https://github.com/centroid457/
Author: Andrei Starichenko
Author-email: centroid@mail.ru
Project-URL: Source, https://github.com/centroid457/classes_aux
Keywords: __cmp__,__getattr__,number,__annotations__,annotations,annots,attributes
Classifier: Topic :: Software Development :: Libraries :: Python Modules
Classifier: License :: OSI Approved :: MIT License
Classifier: Programming Language :: Python
Classifier: Programming Language :: Python :: 3 :: Only
Classifier: Programming Language :: Python :: 3.11
Classifier: Operating System :: OS Independent
Classifier: Intended Audience :: Developers
Classifier: Natural Language :: English
Classifier: Typing :: Typed
Requires-Python: >=3.6
License-File: LICENSE
